django_sqlformatter
