Metadata-Version: 1.1
Name: django-sqlformatter
Version: 1.0.2
Summary: Better SQL formatter for Django
Home-page: http://github.com/gabrielhora/django_sqlformatter
Author: Gabriel Hora
Author-email: gabrielhora@gmail.com
License: MIT
Keywords: django formatter logging
Platform: UNKNOWN
Classifier: Development Status :: 4 - Beta
Classifier: Intended Audience :: Developers
Classifier: License :: OSI Approved :: MIT License
Classifier: Programming Language :: Python :: 3
